<locales>

    <groups name="quiqqer/system">

        <locale name="permissions.message.save.success">
            <de><![CDATA[Zugriffsrechte erfolgreich gespeichert.]]></de>
            <en><![CDATA[Permissions successfuly saved.]]></en>
        </locale>
        <locale name="permissions.message.delete.success">
            <de><![CDATA[Zugriffsrecht erfolgreich gelöscht.]]></de>
            <en><![CDATA[Permission successfuly deleted.]]></en>
        </locale>

        <locale name="exception.permission.session.expired">
            <de><![CDATA[Ihre Sitzung ist abgelaufen, bitte loggen Sie sich ein.]]></de>
            <en><![CDATA[Your session has expired, please login.]]></en>
        </locale>
        <locale name="exception.no.permission">
            <de><![CDATA[Sie haben nicht die nötigen Rechte um diese Aktion durchzuführen.]]></de>
            <en><![CDATA[You have not the necessary rights to perform this action.]]></en>
        </locale>
        <locale name="exception.permissions.exists">
            <de><![CDATA[Das Zugriffsrecht existiert bereits.]]></de>
            <en><![CDATA[The Permission still exists.]]></en>
        </locale>
        <locale name="exception.permissions.permission.not.found">
            <de><![CDATA[Das Zugriffsrecht wurde nicht gefunden.]]></de>
            <en><![CDATA[The Permission could not be found.]]></en>
        </locale>
        <locale name="exception.permissions.delete.only.user.permissions">
            <de><![CDATA[Dieses Zugriffsrecht kann nicht gelöscht werden. Sie können nur Benutzer angelegt Zugriffsrechte löschen.]]></de>
            <en><![CDATA[This permission can not be deleted. You can only delete user created permissions.]]></en>
        </locale>

    </groups>


    <groups name="locale/permissions" datatype="js,php">
        <locale name="quiqqer._title">
            <de><![CDATA[QUIQQER]]></de>
            <en><![CDATA[QUIQQER]]></en>
        </locale>

        <locale name="quiqqer.su._title">
            <de><![CDATA[Ist Super-User]]></de>
            <en><![CDATA[Is Super-User]]></en>
        </locale>
        <locale name="quiqqer.su._description">
            <de><![CDATA[Darf Super-User bearbeiten / erstellen.]]></de>
            <en><![CDATA[Is allowed to create / edit Super-Users.]]></en>
        </locale>

        <locale name="quiqqer.system._title">
            <de><![CDATA[System]]></de>
            <en><![CDATA[System]]></en>
        </locale>
            <locale name="quiqqer.system.update._title">
                <de><![CDATA[Darf Updates durchführen]]></de>
                <en><![CDATA[Is allowed to perform updates.]]></en>
            </locale>

            <locale name="quiqqer.system.permissions._title">
                <de><![CDATA[Darf Zugrifssrechte verwalten.]]></de>
                <en><![CDATA[Is allowed to edit permissions.]]></en>
            </locale>

            <locale name="quiqqer.system.cache._title">
                <de><![CDATA[Darf Cache löschen.]]></de>
                <en><![CDATA[Is allowed to delet the cache.]]></en>
            </locale>
            <locale name="quiqqer.system.console._title">
                <de><![CDATA[Darf sich in die QUIQQER Konsole einloggen.]]></de>
                <en><![CDATA[Is allowed to login in the QUIQQER Console.]]></en>
            </locale>


        <locale name="quiqqer.admin._title">
            <de><![CDATA[Administration]]></de>
            <en><![CDATA[Administration]]></en>
        </locale>
        <locale name="quiqqer.admin._description">
            <de><![CDATA[Kann sich in den Administrationbereich anmelden.]]></de>
            <en><![CDATA[Can login on to the administration.]]></en>
        </locale>

            <locale name="quiqqer.admin.site._title">
                <de><![CDATA[Seiten]]></de>
                <en><![CDATA[Sites]]></en>
            </locale>

            <locale name="quiqqer.admin.groups._title">
                <de><![CDATA[Gruppen]]></de>
                <en><![CDATA[Groups]]></en>
            </locale>
                <locale name="quiqqer.admin.groups.view._title">
                    <de><![CDATA[Darf die Gruppenverwaltung sehen.]]></de>
                    <en><![CDATA[Is allowed to see the group management.]]></en>
                </locale>
                <locale name="quiqqer.admin.groups.edit._title">
                    <de><![CDATA[Darf Gruppen editieren]]></de>
                    <en><![CDATA[Is allowed to edit groups]]></en>
                </locale>

            <locale name="quiqqer.admin.users._title">
                <de><![CDATA[Benutzer]]></de>
                <en><![CDATA[Users]]></en>
            </locale>
                <locale name="quiqqer.admin.users.view._title">
                    <de><![CDATA[Darf die Benutzerverwaltung sehen]]></de>
                    <en><![CDATA[Is allowed to see the user management]]></en>
                </locale>
                <locale name="quiqqer.admin.users.edit._title">
                    <de><![CDATA[Darf Benutzer editieren.]]></de>
                    <en><![CDATA[Is allowed to edit users.]]></en>
                </locale>

            <locale name="quiqqer.projects._title">
                <de><![CDATA[Projekte]]></de>
                <en><![CDATA[Projects]]></en>
            </locale>
                <locale name="quiqqer.projects.create._title">
                    <de><![CDATA[Darf Projekte anlegen.]]></de>
                    <en><![CDATA[Is allowed to creat projects.]]></en>
                </locale>
                <locale name="quiqqer.projects.create._description">
                    <de><![CDATA[Projekte anlegen erlaubt es, neue Projekt im System zu erstellen.]]></de>
                    <en><![CDATA[Creating projects makes it possible to create new project in the system.]]></en>
                </locale>

                <locale name="quiqqer.projects.destroy._title">
                    <de><![CDATA[Darf Projekte löschen.]]></de>
                    <en><![CDATA[Is allowed to delete projects.]]></en>
                </locale>
                <locale name="quiqqer.projects.destroy._description">
                    <de><![CDATA[Darf komplette Projekte löschen. Alle Inhalt eines Projektes können somit unwiederruflich gelöscht werden.]]></de>
                    <en><![CDATA[Can delete entire projects. All content of a project can thus be deleted irrevocably.]]></en>
                </locale>

                <locale name="quiqqer.projects.setconfig._title">
                    <de><![CDATA[Darf Projekt Einstellungen ändern.]]></de>
                    <en><![CDATA[Is allowed to edit project settings.]]></en>
                </locale>
                <locale name="quiqqer.projects.setconfig._description">
                    <de><![CDATA[Darf alle Einstellungen von Projekte editieren / ändern.]]></de>
                    <en><![CDATA[Is allowed to edit all project settings.]]></en>
                </locale>


                <locale name="quiqqer.projects.sites._title">
                    <de><![CDATA[Mehrere Seiten]]></de>
                    <en><![CDATA[More Pages]]></en>
                </locale>

                <locale name="quiqqer.projects.site._title">
                    <de><![CDATA[Eine Seite]]></de>
                    <en><![CDATA[One Page]]></en>
                </locale>

                    <locale name="quiqqer.projects.site.set_permissions._title">
                        <de><![CDATA[Darf Zugriffsrechte auf Seiten setzen und bearbeiten.]]></de>
                        <en><![CDATA[Is allowed to set / edit permissions from pages.]]></en>
                    </locale>
                    <locale name="quiqqer.projects.site.set_permissions._description" html="true">
                        <de><![CDATA[&nbsp;]]></de>
                        <en><![CDATA[&nbsp;]]></en>
                    </locale>

                    <locale name="quiqqer.projects.sites.edit._title">
                        <de><![CDATA[Darf Seiten bearbeiten.]]></de>
                        <en><![CDATA[Is allowed to edit pages.]]></en>
                    </locale>
                    <locale name="quiqqer.projects.site.edit._description" html="true">
                        <de><![CDATA[&nbsp;]]></de>
                        <en><![CDATA[&nbsp;]]></en>
                    </locale>

                    <locale name="quiqqer.projects.site.view._title">
                        <de><![CDATA[Darf die Seite besuchen.]]></de>
                        <en><![CDATA[Is allowed to visit the site.]]></en>
                    </locale>
                    <locale name="quiqqer.projects.site.view._description" html="true">
                        <de><![CDATA[&nbsp;]]></de>
                        <en><![CDATA[&nbsp;]]></en>
                    </locale>

                    <locale name="quiqqer.projects.site.edit._title">
                        <de><![CDATA[Darf die Seite bearbeiten.]]></de>
                        <en><![CDATA[Is allowed to edit the page.]]></en>
                    </locale>
                    <locale name="quiqqer.projects.site.edit._description" html="true">
                        <de><![CDATA[&nbsp;]]></de>
                        <en><![CDATA[&nbsp;]]></en>
                    </locale>

                    <locale name="quiqqer.projects.site.del._title">
                        <de><![CDATA[Darf die Seite löschen.]]></de>
                        <en><![CDATA[Is allowed to delete the page.]]></en>
                    </locale>
                    <locale name="quiqqer.projects.site.del._description" html="true">
                        <de><![CDATA[&nbsp;]]></de>
                        <en><![CDATA[&nbsp;]]></en>
                    </locale>

                    <locale name="quiqqer.projects.site.new._title">
                        <de><![CDATA[Darf neue Unterseite anlegen.]]></de>
                        <en><![CDATA[Is allowed to create new children pages.]]></en>
                    </locale>
                    <locale name="quiqqer.projects.site.new._description" html="true">
                        <de><![CDATA[&nbsp;]]></de>
                        <en><![CDATA[&nbsp;]]></en>
                    </locale>


            <locale name="quiqqer.editors._title">
                <de><![CDATA[Editor / WYSIWYG]]></de>
                <en><![CDATA[Editor / WYSIWYG]]></en>
            </locale>

                <locale name="quiqqer.editors.toolbar._title">
                    <de><![CDATA[Editor / WYSIWYG Toolbar]]></de>
                    <en><![CDATA[Editor / WYSIWYG Toolbar]]></en>
                </locale>

                <locale name="quiqqer.editors.toolbar.delete._title">
                    <de><![CDATA[Darf Editor Toolbars löschen]]></de>
                    <en><![CDATA[Is allowed to delete editor toolbars]]></en>
                </locale>

                <locale name="quiqqer.editors.toolbar.delete._description">
                    <de><![CDATA[Kann angelegt Toolbars für einen WYSIWYG Editor löschen.]]></de>
                    <en><![CDATA[Is allowed to delete created WYSIWYG editor toolbars.]]></en>
                </locale>


    </groups>

</locales>